ipfspy/__init__.py
ipfspy/_modidx.py
ipfspy/_nbdev.py
ipfspy/estuaryapi.py
ipfspy/ipfshttpapi.py
ipfspy/pinataapi.py
ipfspy/tracing.py
ipfspy/utils.py
ipfspy/ipfsspec/__init__.py
ipfspy/ipfsspec/asyn.py
ipfspy/ipfsspec/bufferedfile.py
ipfspy/ipfsspec/gateway.py
ipfspy-0.0.15.dist-info/LICENSE
ipfspy-0.0.15.dist-info/METADATA
ipfspy-0.0.15.dist-info/WHEEL
ipfspy-0.0.15.dist-info/entry_points.txt
ipfspy-0.0.15.dist-info/top_level.txt
ipfspy-0.0.15.dist-info/RECORD
