Metadata-Version: 2.1
Name: ipfspy
Version: 0.0.15
Summary: A python library by Algovera to interact with IPFS and IPFS ecosystem such as the common pinning services
Home-page: https://github.com/AlgoveraAI/ipfspy/tree/master
Author: algovera
Author-email: hello@algovera.ai
License: Apache Software License 2.0
Keywords: ipfs,web3,storage,pinata,estuary
Platform: UNKNOWN
Classifier: Development Status :: 3 - Alpha
Classifier: Intended Audience :: Developers
Classifier: Natural Language :: English
Classifier: Programming Language :: Python :: 3.6
Classifier: Programming Language :: Python :: 3.7
Classifier: Programming Language :: Python :: 3.8
Classifier: Programming Language :: Python :: 3.9
Classifier: Programming Language :: Python :: 3.10
Classifier: License :: OSI Approved :: Apache Software License
Requires-Python: >=3.6
License-File: LICENSE
Requires-Dist: requests (==2.27.1)
Requires-Dist: fastcore
Requires-Dist: pandas
Requires-Dist: ipfshttpclient (==0.7.0)
Requires-Dist: dag-cbor
Requires-Dist: fsspec
Requires-Dist: ipfsspec
Requires-Dist: imageio
Provides-Extra: dev
Requires-Dist: fastai ; extra == 'dev'
